prwlock-0.4.1.dist-info/RECORD
prwlock-0.4.1.dist-info/WHEEL
prwlock-0.4.1.dist-info/metadata.json
prwlock-0.4.1.dist-info/DESCRIPTION.rst
prwlock-0.4.1.dist-info/METADATA
prwlock-0.4.1.dist-info/top_level.txt
prwlock/wrwlock.py
prwlock/prwlock.py
prwlock/__init__.py
prwlock/tests/test_wrwlock.py
prwlock/tests/test_prwlock.py
prwlock/tests/__init__.py
